llm_research/__init__.py
llm_research/model/base_model.py
llm_research/model/models.py
llm_research/model/prompt.py
llm_research/model/utils.py
llm_research/utils.py
llm_research-0.2.0.dist-info/LICENSE
llm_research-0.2.0.dist-info/METADATA
llm_research-0.2.0.dist-info/WHEEL
llm_research-0.2.0.dist-info/RECORD
